HISTORY.rst
LICENSE
MANIFEST.in
README.md
README.rst
setup.cfg
setup.py
docs/Makefile
docs/make.bat
docs/source/HISTORY.rst
docs/source/client.rst
docs/source/conf.py
docs/source/index.rst
docs/source/manager.rst
docs/source/model.rst
docs/source/usage.rst
queryset_client/__init__.py
queryset_client/client.py
queryset_client/tests/__init__.py
queryset_client/tests/settings.py
queryset_client/tests/settings_base.py
queryset_client/tests/testcases.py
queryset_client/tests/base/__init__.py
queryset_client/tests/base/forms.py
queryset_client/tests/base/models.py
queryset_client/tests/base/tests/__init__.py
queryset_client/tests/base/tests/count.py
queryset_client/tests/base/tests/create.py
queryset_client/tests/base/tests/exists.py
queryset_client/tests/base/tests/foreignkey.py
queryset_client/tests/base/tests/get_or_create.py
queryset_client/tests/base/tests/latest.py
queryset_client/tests/base/tests/lazy.py
queryset_client/tests/base/tests/len.py
queryset_client/tests/base/tests/many_to_many.py
queryset_client/tests/base/tests/model.py
queryset_client/tests/base/tests/order_by.py
queryset_client/tests/base/tests/paginator.py
queryset_client/tests/base/tests/slice.py
queryset_client/tests/base/tests/strict.py
queryset_client/tests/base/tests/utils.py
tastypie_queryset_client_p3k.egg-info/PKG-INFO
tastypie_queryset_client_p3k.egg-info/SOURCES.txt
tastypie_queryset_client_p3k.egg-info/dependency_links.txt
tastypie_queryset_client_p3k.egg-info/requires.txt
tastypie_queryset_client_p3k.egg-info/top_level.txt