Metadata-Version: 1.1
Name: tastypie-queryset-client-p3k
Version: 0.7.2
Summary: Client for Tastypie. Provide operation similar to the Django Model API
Home-page: https://github.com/ikeikeikeike/tastypie-queryset-client
Author: Tatsuo Ikeda
Author-email: jp.ne.co.jp at gmail
License: MIT License
Keywords: tastypie,client,django,rest,api
Platform: UNKNOWN
Classifier: Development Status :: 4 - Beta
Classifier: Development Status :: 5 - Production/Stable
Classifier: Framework :: Django
Classifier: Environment :: Web Environment
Classifier: Intended Audience :: Developers
Classifier: License :: OSI Approved :: MIT License
Classifier: Programming Language :: Python
Classifier: Programming Language :: Python :: 2
Classifier: Programming Language :: Python :: 3
Classifier: Topic :: Utilities
Classifier: Topic :: Software Development :: Libraries :: Python Modules
